kstash/__init__.py
kstash/address.py
kstash/api.py
kstash/backend.py
kstash/backend_base.py
kstash/backend_http.py
kstash/backend_inline.py
kstash/backend_mem.py
kstash/backend_s3.py
kstash/config.py
kstash/exceptions.py
kstash/py.typed
kstash/stash.py
kstash-0.2.0.dist-info/METADATA
kstash-0.2.0.dist-info/WHEEL
kstash-0.2.0.dist-info/licenses/LICENSE
kstash-0.2.0.dist-info/RECORD
