Metadata-Version: 2.4
Name: kstash
Version: 0.2.0
Summary: Stashed payloads with nice URIs
Project-URL: Homepage, https://github.com/ccortezia/kstash
Author-email: Cristiano Cortezia <cristiano.cortezia@gmail.com>
License-Expression: MIT
License-File: LICENSE
Classifier: Development Status :: 4 - Beta
Classifier: Programming Language :: Python
Requires-Python: >=3.13
Requires-Dist: boto3>=1.38.16
Requires-Dist: msgpack>=1.1.0
Requires-Dist: requests>=2.32.3
Requires-Dist: types-boto3-s3>=1.38.0
Requires-Dist: types-boto3>=1.38.18
Requires-Dist: types-urllib3>=1.26.25.14
